energyplus_parser/__init__.py
energyplus_parser/parseidf.py
energyplus_parser/parsetab.py
energyplus_parser-0.0.1.dist-info/LICENSE.txt
energyplus_parser-0.0.1.dist-info/METADATA
energyplus_parser-0.0.1.dist-info/WHEEL
energyplus_parser-0.0.1.dist-info/entry_points.txt
energyplus_parser-0.0.1.dist-info/top_level.txt
energyplus_parser-0.0.1.dist-info/RECORD
