Metadata-Version: 2.1
Name: energyplus_parser
Version: 0.0.1
Summary: A simple toolkit for parsing EnergyPlus IDF files and generating 2D/3D visualisations of the geometry. Based on the parseidf module by Daren Thomas.
Author-email: Dillon Loh <loh.dillon@gmail.com>
License: The MIT License (MIT)
Project-URL: Homepage, https://github.com/dillonloh/energyplus_parser
Keywords: simulation,parsing,energyplus,idf
Classifier: License :: OSI Approved :: MIT License
Classifier: Programming Language :: Python
Classifier: Programming Language :: Python :: 3
Requires-Python: >=3.9
License-File: LICENSE.txt
Requires-Dist: matplotlib
Requires-Dist: ply
Requires-Dist: numpy ==1.26.4
Requires-Dist: plotly
